{
  "slides" : [
    {"title": "Reddit", "image": "http://i.qkme.me/3r2fxm.jpg"},
    {"title": "Keyboard Cat", "youtube": "//www.youtube.com/embed/J---aiyznGQ"},
    {"title": "Fibonacci Pigeons", "image": "http://mathblag.files.wordpress.com/2011/11/fibonacci_pigeons.jpg"},
    {"title": "Batman Cat", "image": "https://i.chzbgr.com/maxW500/7670554368/hA827CEEC/"},
    {"title": "Grumpy Cat", "image": "https://i.chzbgr.com/maxW500/7704344064/h64A5357B/"},
    {"d3": "d3-shape"},
    {"title": "ERMAHGERD!", "image": "http://i1.kym-cdn.com/photos/images/newsfeed/000/333/003/0d3.jpg"}
  ] 
}